odoo/addons/account_invoice_line_default_account/README.rst
odoo/addons/account_invoice_line_default_account/__init__.py
odoo/addons/account_invoice_line_default_account/__manifest__.py
odoo/addons/account_invoice_line_default_account/i18n/account_invoice_line_default_account.pot
odoo/addons/account_invoice_line_default_account/i18n/es.po
odoo/addons/account_invoice_line_default_account/i18n/fr.po
odoo/addons/account_invoice_line_default_account/i18n/it.po
odoo/addons/account_invoice_line_default_account/i18n/nl.po
odoo/addons/account_invoice_line_default_account/models/__init__.py
odoo/addons/account_invoice_line_default_account/models/account_move_line.py
odoo/addons/account_invoice_line_default_account/models/res_partner.py
odoo/addons/account_invoice_line_default_account/readme/CONTRIBUTORS.rst
odoo/addons/account_invoice_line_default_account/readme/DESCRIPTION.rst
odoo/addons/account_invoice_line_default_account/readme/ROADMAP.rst
odoo/addons/account_invoice_line_default_account/static/description/icon.png
odoo/addons/account_invoice_line_default_account/static/description/index.html
odoo/addons/account_invoice_line_default_account/tests/__init__.py
odoo/addons/account_invoice_line_default_account/tests/common.py
odoo/addons/account_invoice_line_default_account/tests/test_default_account.py
odoo/addons/account_invoice_line_default_account/tests/test_default_account_supplier.py
odoo/addons/account_invoice_line_default_account/views/res_partner.xml
odoo_addon_account_invoice_line_default_account-16.0.1.0.0.3.dist-info/METADATA
odoo_addon_account_invoice_line_default_account-16.0.1.0.0.3.dist-info/WHEEL
odoo_addon_account_invoice_line_default_account-16.0.1.0.0.3.dist-info/top_level.txt
odoo_addon_account_invoice_line_default_account-16.0.1.0.0.3.dist-info/RECORD
