Metadata-Version: 2.1
Name: odoo-addon-account-invoice-line-default-account
Version: 16.0.1.0.0.3
Summary: Account Invoice Line Default Account
Home-page: https://github.com/OCA/account-invoicing
Author: Therp BV,BCIM,Odoo Community Association (OCA)
Author-email: support@odoo-community.org
License: AGPL-3
Platform: UNKNOWN
Classifier: Programming Language :: Python
Classifier: Framework :: Odoo
Classifier: Framework :: Odoo :: 16.0
Classifier: License :: OSI Approved :: GNU Affero General Public License v3
Requires-Python: >=3.10
Requires-Dist: odoo-addon-base-partition <16.1dev,>=16.0dev
Requires-Dist: odoo <16.1dev,>=16.0a
